airflow/providers/dbt/cloud/__init__.py
airflow/providers/dbt/cloud/get_provider_info.py
airflow/providers/dbt/cloud/version_compat.py
airflow/providers/dbt/cloud/hooks/__init__.py
airflow/providers/dbt/cloud/hooks/dbt.py
airflow/providers/dbt/cloud/operators/__init__.py
airflow/providers/dbt/cloud/operators/dbt.py
airflow/providers/dbt/cloud/sensors/__init__.py
airflow/providers/dbt/cloud/sensors/dbt.py
airflow/providers/dbt/cloud/triggers/__init__.py
airflow/providers/dbt/cloud/triggers/dbt.py
airflow/providers/dbt/cloud/utils/__init__.py
airflow/providers/dbt/cloud/utils/openlineage.py
apache_airflow_providers_dbt_cloud-4.6.3.dist-info/entry_points.txt
apache_airflow_providers_dbt_cloud-4.6.3.dist-info/licenses/LICENSE
apache_airflow_providers_dbt_cloud-4.6.3.dist-info/licenses/NOTICE
apache_airflow_providers_dbt_cloud-4.6.3.dist-info/WHEEL
apache_airflow_providers_dbt_cloud-4.6.3.dist-info/METADATA
apache_airflow_providers_dbt_cloud-4.6.3.dist-info/RECORD
